README.md
setup.py
digit/__init__.py
digit/digit.py
digit.egg-info/PKG-INFO
digit.egg-info/SOURCES.txt
digit.egg-info/dependency_links.txt
digit.egg-info/entry_points.txt
digit.egg-info/requires.txt
digit.egg-info/top_level.txt