Metadata-Version: 1.1
Name: digit
Version: 1.0.1
Summary: Dig git information from .git
Home-page: https://github.com/bongtrop/digit
Author: Pongsakorn Sommalai
Author-email: bongtrop@gmail.com
License: MIT
Download-URL: https://github.com/bongtrop/digit/archive/v1.0.1.tar.gz
Keywords: git,tool,hack
Platform: UNKNOWN
Classifier: Development Status :: 3 - Alpha
Classifier: Intended Audience :: Other Audience
Classifier: License :: OSI Approved :: MIT License
Classifier: Topic :: Utilities
Classifier: Programming Language :: Python :: 2
Classifier: Programming Language :: Python :: 2.7
